zappadock/__init__.py
zappadock/zappadock.py
zappadock-0.1.10.dist-info/LICENCE
zappadock-0.1.10.dist-info/METADATA
zappadock-0.1.10.dist-info/WHEEL
zappadock-0.1.10.dist-info/entry_points.txt
zappadock-0.1.10.dist-info/top_level.txt
zappadock-0.1.10.dist-info/RECORD
