Metadata-Version: 2.1
Name: zappadock
Version: 0.1.10
Summary: A tool for running Zappa commands in a Lambda-like' environment.
Home-page: https://github.com/dickermoshe/zappadock
Author: Moshe Dicker
Author-email: dickermoshe@gmail.com
License: GNU General Public License v3.0
Requires-Python: >=3.6,!=3.10.*,!=3.11.*
License-File: LICENCE
Requires-Dist: Click
Requires-Dist: docker
